rna_cd/__init__.py
rna_cd/bam_process.py
rna_cd/cli.py
rna_cd/models.py
rna_cd/utils.py
rna_cd-0.2.0.dist-info/LICENSE
rna_cd-0.2.0.dist-info/METADATA
rna_cd-0.2.0.dist-info/WHEEL
rna_cd-0.2.0.dist-info/entry_points.txt
rna_cd-0.2.0.dist-info/top_level.txt
rna_cd-0.2.0.dist-info/RECORD
