Metadata-Version: 2.1
Name: rna-cd
Version: 0.2.0
Summary: RNA contamination detector
Home-page: https://github.com/LUMC/rna_cd
Author: Leiden University Medical Center
Author-email: a.h.b.bollen@lumc.nl
License: AGPLv3+
Platform: UNKNOWN
Classifier: License :: OSI Approved :: GNU Affero General Public License v3 or later (AGPLv3+)
Classifier: Programming Language :: Python :: 3 :: Only
Classifier: Programming Language :: Python :: 3.5
Classifier: Programming Language :: Python :: 3.6
Classifier: Programming Language :: Python :: 3.7
Classifier: Topic :: Scientific/Engineering :: Bio-Informatics
Requires-Python: >=3.5
Requires-Dist: click
Requires-Dist: scikit-learn
Requires-Dist: pysam
Requires-Dist: matplotlib
Requires-Dist: joblib
